django_flex_report-0.9.21.dist-info/licenses/LICENSE
flex_report/__init__.py
flex_report/_version.py
flex_report/admin.py
flex_report/app_settings.py
flex_report/apps.py
flex_report/choices.py
flex_report/constants.py
flex_report/fields.py
flex_report/filterset.py
flex_report/forms.py
flex_report/managers.py
flex_report/mixins.py
flex_report/models.py
flex_report/urls.py
flex_report/utils.py
flex_report/views.py
flex_report/defaults/__init__.py
flex_report/defaults/admin.py
flex_report/defaults/views.py
flex_report/migrations/0001_initial.py
flex_report/migrations/0002_alter_column_title.py
flex_report/migrations/0003_column_groups_column_users_tablebutton_groups_and_more.py
flex_report/migrations/0004_column_creator.py
flex_report/migrations/0005_template_model_user_path.py
flex_report/migrations/0006_tablebutton_query_strings.py
flex_report/migrations/0007_remove_template_buttons_alter_template_columns.py
flex_report/migrations/0008_template_buttons.py
flex_report/migrations/0009_alter_template_buttons.py
flex_report/migrations/0010_alter_column_model_alter_template_model_and_more.py
flex_report/migrations/0011_alter_template_model_user_path.py
flex_report/migrations/0012_tablebuttoncolor_alter_tablebutton_color.py
flex_report/migrations/0013_column_column_type.py
flex_report/migrations/0014_alter_column_column_type.py
flex_report/migrations/0015_remove_column_column_type.py
flex_report/migrations/0016_column_column_type.py
flex_report/migrations/0017_remove_column_groups_remove_column_users_and_more.py
flex_report/migrations/0018_alter_tablebutton_title.py
flex_report/migrations/0019_templatesavedfilter.py
flex_report/migrations/0020_templatesavedfilter_created_and_more.py
flex_report/migrations/0021_alter_templatesavedfilter_unique_together_and_more.py
flex_report/migrations/0022_alter_templatesavedfilter_unique_together_and_more.py
flex_report/migrations/0023_alter_template_created_date_and_more.py
flex_report/migrations/0024_alter_templatesavedfilter_unique_together_and_more.py
django_flex_report-0.9.21.dist-info/METADATA
django_flex_report-0.9.21.dist-info/WHEEL
django_flex_report-0.9.21.dist-info/top_level.txt
django_flex_report-0.9.21.dist-info/RECORD
