Metadata-Version: 2.4
Name: django-flex-report
Version: 0.9.21
Summary: A Django app to create flexible reports
Author-email: Saman Zand Haghighi <samanzandh@gmail.com>
License: MIT
Project-URL: Homepage, http://github.com/saman-zand-h/django-flex-report
Classifier: Development Status :: 3 - Alpha
Classifier: Environment :: Web Environment
Classifier: Framework :: Django
Classifier: Intended Audience :: Developers
Classifier: License :: OSI Approved :: MIT License
Classifier: Operating System :: OS Independent
Classifier: Framework :: Django
Classifier: Framework :: Django :: 3.2
Classifier: Framework :: Django :: 4.0
Classifier: Framework :: Django :: 4.1
Classifier: Programming Language :: Python
Classifier: Programming Language :: Python :: 3
Classifier: Programming Language :: Python :: 3 :: Only
Classifier: Programming Language :: Python :: 3.8
Classifier: Programming Language :: Python :: 3.9
Classifier: Programming Language :: Python :: 3.10
Classifier: Programming Language :: Python :: 3.11
Classifier: Topic :: Software Development :: Libraries :: Python Modules
Requires-Python: >=3.8
License-File: LICENSE
Requires-Dist: convertdate>=2.4.0
Requires-Dist: dateparser>=1.1.0
Requires-Dist: Django>=4.2.7
Requires-Dist: django-better-admin-arrayfield>=1.4.2
Requires-Dist: django-classy-tags>=4.1.0
Requires-Dist: django-filter>=23.4
Requires-Dist: django-jalali>=6.0.1
Requires-Dist: django-money>=3.4.0
Requires-Dist: django-phonenumber-field>=7.2.0
Requires-Dist: django-sekizai>=4.1.0
Requires-Dist: django-sortedm2m>=3.1.1
Requires-Dist: django-template-partials>=23.4
Requires-Dist: jdatetime>=4.1.1
Requires-Dist: numpy>=1.26.2
Requires-Dist: pandas>=2.0.0
Requires-Dist: phonenumbers>=8.13.25
Requires-Dist: py-moneyed>=3.0
Requires-Dist: python-dateutil>=2.8.2
Requires-Dist: pytz>=2023.3.post1
Requires-Dist: typing_extensions>=4.8.0
Requires-Dist: xlwt>=1.3.0
Dynamic: license-file
